fastminer/__init__.py
fastminer/fast/__init__.py
fastminer/fast/closed.py
fastminer/jars/fastminer.jar
fastminer/jars/spmf.jar
fastminer/spmf/__init__.py
fastminer/spmf/base.py
fastminer/spmf/neclatclosed.py
fastminer-0.1.1.dist-info/WHEEL
fastminer-0.1.1.dist-info/METADATA
fastminer-0.1.1.dist-info/RECORD
