Metadata-Version: 2.1
Name: fastminer
Version: 0.1.1
Summary: fast data mining algos
Author: Tony
Requires-Python: >=3.9,<4.0
Classifier: Programming Language :: Python :: 3
Classifier: Programming Language :: Python :: 3.10
Classifier: Programming Language :: Python :: 3.9
Requires-Dist: pydantic (>=1.9.1,<2.0.0)
Requires-Dist: pyjnius (>=1.4.1,<2.0.0)
